toggl_fetch/__init__.py
toggl_fetch/api.py
toggl_fetch/app_version.py
toggl_fetch/fetch.py
toggl_fetch-1.0.1.dist-info/DESCRIPTION.rst
toggl_fetch-1.0.1.dist-info/METADATA
toggl_fetch-1.0.1.dist-info/RECORD
toggl_fetch-1.0.1.dist-info/WHEEL
toggl_fetch-1.0.1.dist-info/entry_points.txt
toggl_fetch-1.0.1.dist-info/metadata.json
toggl_fetch-1.0.1.dist-info/top_level.txt
