Metadata-Version: 2.0
Name: toggl-fetch
Version: 1.0.1
Summary: Fetch summary reports from Toggl.com, with automatic date range calculation.
Home-page: https://github.com/Tblue/toggl-fetch
Author: Tilman Blumenbach
Author-email: tilman+pypi@ax86.net
License: UNKNOWN
Keywords: toggl report export
Platform: UNKNOWN
Classifier: Development Status :: 5 - Production/Stable
Classifier: Environment :: Console
Classifier: Intended Audience :: End Users/Desktop
Classifier: License :: OSI Approved :: GNU General Public License v3 or later (GPLv3+)
Classifier: Natural Language :: English
Classifier: Operating System :: OS Independent
Classifier: Programming Language :: Python :: 3.5
Classifier: Programming Language :: Python :: 3 :: Only
Classifier: Topic :: Office/Business
Classifier: Topic :: Utilities
Requires-Dist: python-dateutil (~=2.0)
Requires-Dist: pyxdg (~=0.20)
Requires-Dist: requests (~=2.2)
